[
{
  "name": "date",
    "pattern": "",
    "icon": "fa-calendar",
    "title": "Data e hora da notícia",
    "required": true,
    "type": {
      "view": "date"
    }
},
{
  "name": "title",
  "title": "Título da notícia",
  "required": true,
  "limit": 140,
  "placeholder": "Informe o título",
  "type": {
    "view": "textarea"
  }
},
{
  "name": "description",
  "title": "Descrição",
  "required": true,
  "limit": 240,
  "placeholder": "Informe o título",
  "type": {
    "view": "textarea"
  }
},
{
  "name": "github",
  "title": "Github",
  "required": true,
  "type": {
    "view": "textarea"
  }
},
{
  "name": "author-name",
  "title": "Author",
  "required": true,
  "type": {
    "view": "textarea"
  }
},
{
  "name": "image",
  "pattern": "",
  "icon": "fa-picture-o",
  "title": "Imagem de Capa",
  "required": true,
  "type": {
    "view": "cover"
  }
}
]
